titiler/openeo/__init__.py
titiler/openeo/auth.py
titiler/openeo/errors.py
titiler/openeo/factory.py
titiler/openeo/main.py
titiler/openeo/middleware.py
titiler/openeo/openapi.yaml
titiler/openeo/py.typed
titiler/openeo/reader.py
titiler/openeo/settings.py
titiler/openeo/stacapi.py
titiler/openeo/models/auth.py
titiler/openeo/models/openapi.py
titiler/openeo/models/udp.py
titiler/openeo/processes/__init__.py
titiler/openeo/processes/data/absolute.json
titiler/openeo/processes/data/add.json
titiler/openeo/processes/data/add_dimension.json
titiler/openeo/processes/data/aggregate_spatial.json
titiler/openeo/processes/data/and.json
titiler/openeo/processes/data/apply.json
titiler/openeo/processes/data/apply_dimension.json
titiler/openeo/processes/data/apply_pixel_selection.json
titiler/openeo/processes/data/arccos.json
titiler/openeo/processes/data/arcosh.json
titiler/openeo/processes/data/arcsin.json
titiler/openeo/processes/data/arctan.json
titiler/openeo/processes/data/arctan2.json
titiler/openeo/processes/data/array_create.json
titiler/openeo/processes/data/array_element.json
titiler/openeo/processes/data/arsinh.json
titiler/openeo/processes/data/artanh.json
titiler/openeo/processes/data/ceil.json
titiler/openeo/processes/data/clip.json
titiler/openeo/processes/data/color_formula.json
titiler/openeo/processes/data/colormap.json
titiler/openeo/processes/data/constant.json
titiler/openeo/processes/data/cos.json
titiler/openeo/processes/data/cosh.json
titiler/openeo/processes/data/count.json
titiler/openeo/processes/data/create_data_cube.json
titiler/openeo/processes/data/divide.json
titiler/openeo/processes/data/e.json
titiler/openeo/processes/data/eq.json
titiler/openeo/processes/data/exp.json
titiler/openeo/processes/data/first.json
titiler/openeo/processes/data/firstpixel.json
titiler/openeo/processes/data/floor.json
titiler/openeo/processes/data/get_colormap.json
titiler/openeo/processes/data/get_param_item.json
titiler/openeo/processes/data/gt.json
titiler_openeo-0.11.0.dist-info/METADATA
titiler_openeo-0.11.0.dist-info/WHEEL
titiler_openeo-0.11.0.dist-info/licenses/LICENSE
titiler_openeo-0.11.0.dist-info/RECORD
