Metadata-Version: 2.4
Name: titiler-openeo
Version: 0.11.0
Summary: TiTiler backend for openEO.
Project-URL: Homepage, https://sentinel-hub.github.io/titiler-openeo/
Project-URL: Documentation, https://sentinel-hub.github.io/titiler-openeo/
Project-URL: Issues, https://github.com/sentinel-hub/titiler-openeo/issues
Project-URL: Source, https://github.com/sentinel-hub/titiler-openeo
Project-URL: Changelog, https://sentinel-hub.github.io/titiler-openeo/release-notes/
Author-email: Vincent Sarago <vincent@developmentseed.com>, Emmanuel Mathot <emmanuel@developmentseed.com>
License: MIT
License-File: LICENSE
Keywords: COG,FastAPI,Mosaic,Rasterio,STAC,TiTiler,openEO,rio-tiler
Classifier: Intended Audience :: Information Technology
Classifier: Intended Audience :: Science/Research
Classifier: License :: OSI Approved :: MIT License
Classifier: Programming Language :: Python :: 3
Classifier: Programming Language :: Python :: 3.10
Classifier: Programming Language :: Python :: 3.11
Classifier: Programming Language :: Python :: 3.12
Classifier: Topic :: Scientific/Engineering :: GIS
Requires-Python: >=3.11
Requires-Dist: jsonpath-ng~=1.7.0
Requires-Dist: openeo-pg-parser-networkx==2026.1.2
Requires-Dist: pydantic-settings~=2.0
Requires-Dist: pystac-client
Requires-Dist: starlette-cramjam<0.6,>=0.4
Requires-Dist: titiler-core>=1.1.1
Provides-Extra: duckdb
Requires-Dist: duckdb; extra == 'duckdb'
Provides-Extra: oidc
Requires-Dist: cryptography; extra == 'oidc'
Requires-Dist: httpx; extra == 'oidc'
Provides-Extra: postgres
Requires-Dist: psycopg2-binary; extra == 'postgres'
Requires-Dist: sqlalchemy>=2.0.0; extra == 'postgres'
Provides-Extra: server
Requires-Dist: uvicorn[standard]<0.19.0,>=0.12.0; extra == 'server'
